[
    {
        "id": "04529efc-10f4-4db3-a683-482fec0297dc",
        "ingles": "hello",
        "espanol": "hola",
        "fecha": "2025-03-19"
    },
    {
        "id": "0d4c3e94-36b2-464f-ba4a-be851c3a3457",
        "ingles": "this is gonna take a while",
        "espanol": "esto va a tardar un rato",
        "fecha": "2025-03-21"
    },
    {
        "id": "8d31fb93-29ed-4c6e-aa34-ea0c4cb00401",
        "ingles": "how long is this gonna take",
        "espanol": "esto cuanto tiempo va a llevar",
        "fecha": "2025-03-21"
    },
    {
        "id": "81c3c44f-31b7-4835-a743-653d6fad661b",
        "ingles": "ok",
        "espanol": "esta bien",
        "fecha": "2025-03-21"
    },
    {
        "id": "091b7d88-ea9e-4894-ad78-0d36fb2a2cf6",
        "ingles": "height",
        "espanol": "alto",
        "fecha": "2025-03-25"
    },
    {
        "id": "bb5f5bb9-5be1-4654-9f2b-b110638a3911",
        "ingles": "yes",
        "espanol": "si",
        "fecha": "2025-03-27"
    },
    {
        "id": "d67a382a-57aa-40ec-893f-bda73f8a911f",
        "ingles": "thank you",
        "espanol": "gracias",
        "fecha": "2025-03-28"
    },
    {
        "id": "4e4bf2b2-c9aa-4fa0-9100-02b898d538ef",
        "ingles": "thats enough",
        "espanol": "eso es suficiente",
        "fecha": "2025-03-28"
    },
    {
        "id": "c26f2c0b-2ccf-4af5-8940-6436947c68c9",
        "ingles": "dont ever do that again",
        "espanol": "no vuelvas a hacerlo",
        "fecha": "2025-03-28"
    }
]